hexdump.py
simple_hexdump-0.0.1.dist-info/METADATA
simple_hexdump-0.0.1.dist-info/WHEEL
simple_hexdump-0.0.1.dist-info/top_level.txt
simple_hexdump-0.0.1.dist-info/RECORD
