Metadata-Version: 2.1
Name: simple-hexdump
Version: 0.0.1
Summary: A simple hexdump module for Python
Home-page: https://gist.github.com/NeatMonster/c06c61ba4114a2b31418a364341c26c0
Author: NeatMonster
Author-email: neat@neat.sh
License: UNKNOWN
Platform: UNKNOWN
Classifier: Programming Language :: Python :: 2
Classifier: Programming Language :: Python :: 3
Classifier: License :: OSI Approved :: MIT License
Classifier: Operating System :: OS Independent
Requires-Python: >=2.6
